rentier_rotating_proxies/__init__.py
rentier_rotating_proxies/expire.py
rentier_rotating_proxies/middlewares.py
rentier_rotating_proxies/policy.py
rentier_rotating_proxies/utils.py
rentier_scrapy_proxy_rotator-0.6.2.dist-info/LICENSE.txt
rentier_scrapy_proxy_rotator-0.6.2.dist-info/METADATA
rentier_scrapy_proxy_rotator-0.6.2.dist-info/WHEEL
rentier_scrapy_proxy_rotator-0.6.2.dist-info/top_level.txt
rentier_scrapy_proxy_rotator-0.6.2.dist-info/RECORD
