Metadata-Version: 2.1
Name: rentier-scrapy-proxy-rotator
Version: 0.6.2
Summary: Rentier Analytics Scrapy Proxy Rotator
Home-page: https://github.com/rentieranalytics/rentier-scrapy-proxy-rotator
Author: Michal Hodur, Mikhail Korobov
Author-email: michal.hodur@rentier.io, kmike84@gmail.com
License: MIT license
Platform: UNKNOWN
Classifier: Development Status :: 3 - Alpha
Classifier: License :: OSI Approved :: MIT License
Classifier: Intended Audience :: Developers
Classifier: Operating System :: OS Independent
Classifier: Framework :: Scrapy
Classifier: Programming Language :: Python
Classifier: Programming Language :: Python :: 2
Classifier: Programming Language :: Python :: 2.7
Classifier: Programming Language :: Python :: 3
Classifier: Programming Language :: Python :: 3.4
Classifier: Programming Language :: Python :: 3.5
Classifier: Programming Language :: Python :: 3.6
Classifier: Programming Language :: Python :: 3.7
Requires-Dist: attrs (>16.0.0)
Requires-Dist: six
Requires-Dist: typing
